neuroevolve/__init__.py
neuroevolve/configs.py
neuroevolve/es.py
neuroevolve/evaluation.py
neuroevolve/genome.py
neuroevolve/logging_utils.py
neuroevolve/operators.py
neuroevolve/selection.py
neuroevolve-0.0.1.dist-info/licenses/LICENSE
neuroevolve-0.0.1.dist-info/METADATA
neuroevolve-0.0.1.dist-info/WHEEL
neuroevolve-0.0.1.dist-info/top_level.txt
neuroevolve-0.0.1.dist-info/RECORD
