Metadata-Version: 2.4
Name: neuroevolve
Version: 0.0.1
Requires-Python: >=3.12
License-File: LICENSE
Requires-Dist: numpy>=1.26
Requires-Dist: torch>=2.3
Requires-Dist: torchvision>=0.18
Requires-Dist: gymnasium>=0.29
Requires-Dist: shimmy>=1.3
Requires-Dist: scikit-learn>=1.3
Requires-Dist: scipy>=1.11
Requires-Dist: matplotlib>=3.8
Requires-Dist: plotly>=5.20
Requires-Dist: networkx>=3.2
Requires-Dist: pillow>=10.0
Requires-Dist: pyyaml>=6.0
Requires-Dist: tqdm>=4.66
Requires-Dist: pytest>=8.0
Requires-Dist: pytest-cov>=4.1
Dynamic: license-file
